filey/__init__.py
filey-0.0.1.dist-info/LICENSE
filey-0.0.1.dist-info/METADATA
filey-0.0.1.dist-info/WHEEL
filey-0.0.1.dist-info/top_level.txt
filey-0.0.1.dist-info/RECORD
