Metadata-Version: 2.1
Name: filey
Version: 0.0.1
Summary: UNKNOWN
Home-page: https://tildegit.org/eli2and40/cabinet
Author: Kenneth Elisandro
Author-email: eli2and40@tilde.club
License: MIT
Keywords: utilities productivity
Platform: UNKNOWN
Classifier: Programming Language :: Python :: 3
Classifier: License :: OSI Approved :: MIT License
Classifier: Operating System :: OS Independent
Requires: filetype
Requires: audio_metadata
Requires: send2trash
Requires: sl4ng
Requires-Python: >=3.8
